mindlakesdk/LICENSE
mindlakesdk/README.md
mindlakesdk/__init__.py
mindlakesdk/cryptor.py
mindlakesdk/datalake.py
mindlakesdk/keyhelper.py
mindlakesdk/message.py
mindlakesdk/permission.py
mindlakesdk/settings.py
mindlakesdk/utils.py
mindlakesdk-1.0.8.dist-info/METADATA
mindlakesdk-1.0.8.dist-info/WHEEL
mindlakesdk-1.0.8.dist-info/licenses/LICENSE
mindlakesdk-1.0.8.dist-info/RECORD
